pyqtCuWi/__init__.py
pyqtCuWi/iconbutton.py
pyqtCuWi/loadingscreen.py
pyqtCuWi/outerradius.py
pyqtCuWi/popup.py
pyqtCuWi/qfboxlayout.py
pyqtCuWi/qhtmleditor.py
pyqtCuWi/qsyntaxhighlight.py
pyqtCuWi/rankwidget.py
pyqtCuWi/tagarea.py
pyqtCuWi/pyqtCuWiErrors/__init__.py
pyqtCuWi/pyqtCuWiModules/__init__.py
pyqtCuWi/pyqtCuWiModules/clearList.py
pyqtCuWi/pyqtCuWiModules/jsonHelper.py
pyqtCuWi/pyqtCuWiModules/progressBar.py
pyqtCuWi-1.4.1.dist-info/LICENSE
pyqtCuWi-1.4.1.dist-info/METADATA
pyqtCuWi-1.4.1.dist-info/WHEEL
pyqtCuWi-1.4.1.dist-info/top_level.txt
pyqtCuWi-1.4.1.dist-info/RECORD
