Metadata-Version: 2.1
Name: pyqtCuWi
Version: 1.4.1
Summary: Custom Widgets For PyQt5
Home-page: https://github.com/myygunduz/pyqtCuWi
Author: Mücahit Yusuf Yasin Gündüz
Author-email: myygunduz@gmail.com
License: UNKNOWN
Project-URL: Documentation, https://github.com/myygunduz/pyqtCuWi/blob/main/documentation.md
Platform: UNKNOWN
Classifier: Programming Language :: Python :: 3
Classifier: License :: OSI Approved :: GNU General Public License v3 (GPLv3)
Classifier: Operating System :: OS Independent
Requires-Python: >=3.6
License-File: LICENSE
Requires-Dist: beautifulsoup4 (>=4.10.0)
Requires-Dist: Pygments (>=2.11.1PyQt5>=5.15.3pyqt5Custom>=1.0.0qt-material>=2.8.18)
